{
    "TotalCount": 166,
    "Items": [
        {
            "Name": "Accounting",
            "Units": 24.0,
            "SubPlanCode": "ACCT-SPEC",
            "SubplanType": "SPC",
            "Year": 2022,
            "Career": "Postgraduate"
        },
        {
            "Name": "Accounting Honours",
            "Units": 48.0,
            "SubPlanCode": "ACCT-HSPC",
            "SubplanType": "SPC",
            "Year": 2022,
            "Career": "Undergraduate"
        },
        {
            "Name": "Actuarial Statistics",
            "Units": 24.0,
            "SubPlanCode": "ASTA-SPEC",
            "SubplanType": "SPC",
            "Year": 2022,
            "Career": "Postgraduate"
        },
        {
            "Name": "Actuarial Studies",
            "Units": 24.0,
            "SubPlanCode": "ACST-SPEC",
            "SubplanType": "SPC",
            "Year": 2022,
            "Career": "Postgraduate"
        },
        {
            "Name": "Advanced Chemistry",
            "Units": 24.0,
            "SubPlanCode": "CHEM-SPEC",
            "SubplanType": "SPC",
            "Year": 2022,
            "Career": "Undergraduate"
        },
        {
            "Name": "Advanced Mathematics",
            "Units": 24.0,
            "SubPlanCode": "ADMA-SPEC",
            "SubplanType": "SPC",
            "Year": 2022,
            "Career": "Undergraduate"
        },
        {
            "Name": "Advanced Physics",
            "Units": 24.0,
            "SubPlanCode": "ADPH-SPEC",
            "SubplanType": "SPC",
            "Year": 2022,
            "Career": "Undergraduate"
        },
        {
            "Name": "Advanced Quantitative Biology and Bioinformatics",
            "Units": 24.0,
            "SubPlanCode": "AQBI-SPEC",
            "SubplanType": "SPC",
            "Year": 2022,
            "Career": "Undergraduate"
        },
        {
            "Name": "Anthropology Honours",
            "Units": 48.0,
            "SubPlanCode": "ANTH-HSPC",
            "SubplanType": "SPC",
            "Year": 2022,
            "Career": "Undergraduate"
        },
        {
            "Name": "Applied Economics Honours",
            "Units": 48.0,
            "SubPlanCode": "APEC-HSPC",
            "SubplanType": "SPC",
            "Year": 2022,
            "Career": "Undergraduate"
        },
        {
            "Name": "Applied Finance",
            "Units": 24.0,
            "SubPlanCode": "APFN-SPEC",
            "SubplanType": "SPC",
            "Year": 2022,
            "Career": "Postgraduate"
        },
        {
            "Name": "Archaeology Honours",
            "Units": 48.0,
            "SubPlanCode": "ARCH-HSPC",
            "SubplanType": "SPC",
            "Year": 2022,
            "Career": "Undergraduate"
        },
        {
            "Name": "Art History and Theory Honours",
            "Units": 48.0,
            "SubPlanCode": "ARTH-HSPC",
            "SubplanType": "SPC",
            "Year": 2022,
            "Career": "Undergraduate"
        },
        {
            "Name": "Art of War",
            "Units": 24.0,
            "SubPlanCode": "AWAR-SPEC",
            "SubplanType": "SPC",
            "Year": 2022,
            "Career": "Postgraduate"
        },
        {
            "Name": "Artificial Intelligence",
            "Units": 24.0,
            "SubPlanCode": "ARIN-SPEC",
            "SubplanType": "SPC",
            "Year": 2022,
            "Career": "Undergraduate"
        },
        {
            "Name": "Artificial Intelligence",
            "Units": 24.0,
            "SubPlanCode": "ARTIF-SPEC",
            "SubplanType": "SPC",
            "Year": 2022,
            "Career": "Postgraduate"
        },
        {
            "Name": "Asia-Pacific Studies Honours",
            "Units": 48.0,
            "SubPlanCode": "ASPA-HSPC",
            "SubplanType": "SPC",
            "Year": 2022,
            "Career": "Undergraduate"
        },
        {
            "Name": "Astronomy and Astrophysics",
            "Units": 24.0,
            "SubPlanCode": "ASAP-SPEC",
            "SubplanType": "SPC",
            "Year": 2022,
            "Career": "Undergraduate"
        },
        {
            "Name": "Astronomy and Astrophysics Honours",
            "Units": 48.0,
            "SubPlanCode": "ASTR-HSPC",
            "SubplanType": "SPC",
            "Year": 2022,
            "Career": "Undergraduate"
        },
        {
            "Name": "Australian Indigenous Studies Honours",
            "Units": 48.0,
            "SubPlanCode": "AINS-HSPC",
            "SubplanType": "SPC",
            "Year": 2022,
            "Career": "Undergraduate"
        },
        {
            "Name": "Bioarchaeology and Forensic Anthropology",
            "Units": 24.0,
            "SubPlanCode": "BAFA-SPEC",
            "SubplanType": "SPC",
            "Year": 2022,
            "Career": "Postgraduate"
        },
        {
            "Name": "Biochemistry",
            "Units": 24.0,
            "SubPlanCode": "BCHM-SPEC",
            "SubplanType": "SPC",
            "Year": 2022,
            "Career": "Undergraduate"
        },
        {
            "Name": "Biological Anthropology Honours",
            "Units": 48.0,
            "SubPlanCode": "BIAN-HSPC",
            "SubplanType": "SPC",
            "Year": 2022,
            "Career": "Undergraduate"
        },
        {
            "Name": "Biology Honours",
            "Units": 48.0,
            "SubPlanCode": "BIOL-HSPC",
            "SubplanType": "SPC",
            "Year": 2022,
            "Career": "Undergraduate"
        },
        {
            "Name": "Biomedical Science",
            "Units": 24.0,
            "SubPlanCode": "BMSC-SPEC",
            "SubplanType": "SPC",
            "Year": 2022,
            "Career": "Undergraduate"
        },
        {
            "Name": "Business Essentials",
            "Units": 24.0,
            "SubPlanCode": "BSNE-SPEC",
            "SubplanType": "SPC",
            "Year": 2022,
            "Career": "Postgraduate"
        },
        {
            "Name": "Business Information Systems Honours",
            "Units": 48.0,
            "SubPlanCode": "BISS-HSPC",
            "SubplanType": "SPC",
            "Year": 2022,
            "Career": "Undergraduate"
        },
        {
            "Name": "Business Information systems",
            "Units": 24.0,
            "SubPlanCode": "BISY-SPEC",
            "SubplanType": "SPC",
            "Year": 2022,
            "Career": "Postgraduate"
        },
        {
            "Name": "Chemistry Honours",
            "Units": 48.0,
            "SubPlanCode": "CHEM-HSPC",
            "SubplanType": "SPC",
            "Year": 2022,
            "Career": "Undergraduate"
        },
        {
            "Name": "Classical Studies Honours",
            "Units": 48.0,
            "SubPlanCode": "CLAS-HSPC",
            "SubplanType": "SPC",
            "Year": 2022,
            "Career": "Undergraduate"
        },
        {
            "Name": "Climate Science Specialisation",
            "Units": 24.0,
            "SubPlanCode": "CLSC-SPEC",
            "SubplanType": "SPC",
            "Year": 2022,
            "Career": "Undergraduate"
        },
        {
            "Name": "Composition Honours",
            "Units": 48.0,
            "SubPlanCode": "CPSN-HSPC",
            "SubplanType": "SPC",
            "Year": 2022,
            "Career": "Undergraduate"
        },
        {
            "Name": "Composition for Film and Video Games Honours",
            "Units": 48.0,
            "SubPlanCode": "CFVG-HSPC",
            "SubplanType": "SPC",
            "Year": 2022,
            "Career": "Undergraduate"
        },
        {
            "Name": "Computational Foundations",
            "Units": 24.0,
            "SubPlanCode": "COMP-SPEC",
            "SubplanType": "SPC",
            "Year": 2022,
            "Career": "Postgraduate"
        },
        {
            "Name": "Computer Science Honours",
            "Units": 48.0,
            "SubPlanCode": "COMP-HSPC",
            "SubplanType": "SPC",
            "Year": 2022,
            "Career": "Undergraduate"
        },
        {
            "Name": "Computer Systems",
            "Units": 24.0,
            "SubPlanCode": "CMSY-SPEC",
            "SubplanType": "SPC",
            "Year": 2022,
            "Career": "Postgraduate"
        },
        {
            "Name": "Computer Systems",
            "Units": 24.0,
            "SubPlanCode": "COMS-SPEC",
            "SubplanType": "SPC",
            "Year": 2022,
            "Career": "Undergraduate"
        },
        {
            "Name": "Computing Essentials",
            "Units": 24.0,
            "SubPlanCode": "CMPE-SPEC",
            "SubplanType": "SPC",
            "Year": 2022,
            "Career": "Postgraduate"
        },
        {
            "Name": "Conflict and Development",
            "Units": 24.0,
            "SubPlanCode": "CODE-SPEC",
            "SubplanType": "SPC",
            "Year": 2022,
            "Career": "Postgraduate"
        },
        {
            "Name": "Contemporary Europe Honours",
            "Units": 48.0,
            "SubPlanCode": "EURO-HSPC",
            "SubplanType": "SPC",
            "Year": 2022,
            "Career": "Undergraduate"
        },
        {
            "Name": "Contemporary Regulation",
            "Units": 24.0,
            "SubPlanCode": "CREG-SPEC",
            "SubplanType": "SPC",
            "Year": 2022,
            "Career": "Postgraduate"
        },
        {
            "Name": "Corporate and Commercial Law",
            "Units": 24.0,
            "SubPlanCode": "COCOM-SPEC",
            "SubplanType": "SPC",
            "Year": 2022,
            "Career": "Undergraduate"
        },
        {
            "Name": "Criminology Honours",
            "Units": 48.0,
            "SubPlanCode": "CRIM-HSPC",
            "SubplanType": "SPC",
            "Year": 2022,
            "Career": "Undergraduate"
        },
        {
            "Name": "Cultural Heritage Management",
            "Units": 24.0,
            "SubPlanCode": "CEHE-SPEC",
            "SubplanType": "SPC",
            "Year": 2022,
            "Career": "Postgraduate"
        },
        {
            "Name": "Data Science",
            "Units": 24.0,
            "SubPlanCode": "DTSC-SPEC",
            "SubplanType": "SPC",
            "Year": 2022,
            "Career": "Postgraduate"
        },
        {
            "Name": "Demography Honours",
            "Units": 48.0,
            "SubPlanCode": "DEMO-HSPC",
            "SubplanType": "SPC",
            "Year": 2022,
            "Career": "Undergraduate"
        },
        {
            "Name": "Development Policy",
            "Units": 24.0,
            "SubPlanCode": "DVPL-SPEC",
            "SubplanType": "SPC",
            "Year": 2022,
            "Career": "Postgraduate"
        },
        {
            "Name": "Development Studies Honours",
            "Units": 48.0,
            "SubPlanCode": "DEST-HSPC",
            "SubplanType": "SPC",
            "Year": 2022,
            "Career": "Undergraduate"
        },
        {
            "Name": "Digital Humanities Honours",
            "Units": 48.0,
            "SubPlanCode": "DIGH-HSPC",
            "SubplanType": "SPC",
            "Year": 2022,
            "Career": "Undergraduate"
        },
        {
            "Name": "Digital Transformation",
            "Units": 24.0,
            "SubPlanCode": "DITR-SPEC",
            "SubplanType": "SPC",
            "Year": 2022,
            "Career": "Postgraduate"
        },
        {
            "Name": "Earth Physics",
            "Units": 24.0,
            "SubPlanCode": "EARP-SPEC",
            "SubplanType": "SPC",
            "Year": 2022,
            "Career": "Undergraduate"
        },
        {
            "Name": "Earth and Marine Science Honours",
            "Units": 48.0,
            "SubPlanCode": "EMSC-HSPC",
            "SubplanType": "SPC",
            "Year": 2022,
            "Career": "Undergraduate"
        },
        {
            "Name": "Economic Policy",
            "Units": 24.0,
            "SubPlanCode": "ECPL-SPEC",
            "SubplanType": "SPC",
            "Year": 2022,
            "Career": "Postgraduate"
        },
        {
            "Name": "Economics Honours",
            "Units": 48.0,
            "SubPlanCode": "ECON-HSPC",
            "SubplanType": "SPC",
            "Year": 2022,
            "Career": "Undergraduate"
        },
        {
            "Name": "Economies of Asia and the Pacific",
            "Units": 24.0,
            "SubPlanCode": "ECAP-SPEC",
            "SubplanType": "SPC",
            "Year": 2022,
            "Career": "Postgraduate"
        },
        {
            "Name": "English Honours",
            "Units": 48.0,
            "SubPlanCode": "ENGL-HSPC",
            "SubplanType": "SPC",
            "Year": 2022,
            "Career": "Undergraduate"
        },
        {
            "Name": "English Language",
            "Units": 24.0,
            "SubPlanCode": "ENGL-SPEC",
            "SubplanType": "SPC",
            "Year": 2022,
            "Career": "Postgraduate"
        },
        {
            "Name": "Entrepreneurship and Innovation",
            "Units": 24.0,
            "SubPlanCode": "ENIN-SPEC",
            "SubplanType": "SPC",
            "Year": 2022,
            "Career": "Postgraduate"
        },
        {
            "Name": "Environment Honours",
            "Units": 48.0,
            "SubPlanCode": "ENVI-HSPC",
            "SubplanType": "SPC",
            "Year": 2022,
            "Career": "Undergraduate"
        },
        {
            "Name": "Environment and Public Policy",
            "Units": 24.0,
            "SubPlanCode": "ENPP-SPEC",
            "SubplanType": "SPC",
            "Year": 2022,
            "Career": "Postgraduate"
        },
        {
            "Name": "Environmental Archaeology and Climate Change",
            "Units": 24.0,
            "SubPlanCode": "EACC-SPEC",
            "SubplanType": "SPC",
            "Year": 2022,
            "Career": "Postgraduate"
        },
        {
            "Name": "Environmental Geology",
            "Units": 24.0,
            "SubPlanCode": "ENGE-SPEC",
            "SubplanType": "SPC",
            "Year": 2022,
            "Career": "Undergraduate"
        },
        {
            "Name": "Environmental Studies Honours",
            "Units": 48.0,
            "SubPlanCode": "ENVS-HSPC",
            "SubplanType": "SPC",
            "Year": 2022,
            "Career": "Undergraduate"
        },
        {
            "Name": "Evolution and Ecology",
            "Units": 24.0,
            "SubPlanCode": "EVEC-SPEC",
            "SubplanType": "SPC",
            "Year": 2022,
            "Career": "Undergraduate"
        },
        {
            "Name": "Finance",
            "Units": 24.0,
            "SubPlanCode": "FINM-SPEC",
            "SubplanType": "SPC",
            "Year": 2022,
            "Career": "Postgraduate"
        },
        {
            "Name": "Finance Honours",
            "Units": 48.0,
            "SubPlanCode": "FINM-HSPC",
            "SubplanType": "SPC",
            "Year": 2022,
            "Career": "Undergraduate"
        },
        {
            "Name": "Foreign Policy Analysis",
            "Units": 24.0,
            "SubPlanCode": "IRFP-SPEC",
            "SubplanType": "SPC",
            "Year": 2022,
            "Career": "Postgraduate"
        },
        {
            "Name": "Foreign and Defence Policy",
            "Units": 24.0,
            "SubPlanCode": "FODF-SPEC",
            "SubplanType": "SPC",
            "Year": 2022,
            "Career": "Postgraduate"
        },
        {
            "Name": "Gender and Development",
            "Units": 24.0,
            "SubPlanCode": "GEDE-SPEC",
            "SubplanType": "SPC",
            "Year": 2022,
            "Career": "Postgraduate"
        },
        {
            "Name": "Gender, Sexuality and Culture Honours",
            "Units": 48.0,
            "SubPlanCode": "GSXC-HSPC",
            "SubplanType": "SPC",
            "Year": 2022,
            "Career": "Undergraduate"
        },
        {
            "Name": "Genetics",
            "Units": 24.0,
            "SubPlanCode": "GENE-SPEC",
            "SubplanType": "SPC",
            "Year": 2022,
            "Career": "Undergraduate"
        },
        {
            "Name": "Geochemistry and Petrology",
            "Units": 24.0,
            "SubPlanCode": "GOPT-SPEC",
            "SubplanType": "SPC",
            "Year": 2022,
            "Career": "Undergraduate"
        },
        {
            "Name": "Geophysics and Geology",
            "Units": 24.0,
            "SubPlanCode": "GEGE-SPEC",
            "SubplanType": "SPC",
            "Year": 2022,
            "Career": "Undergraduate"
        },
        {
            "Name": "Global Development Policy",
            "Units": 24.0,
            "SubPlanCode": "GLDV-SPEC",
            "SubplanType": "SPC",
            "Year": 2022,
            "Career": "Postgraduate"
        },
        {
            "Name": "Health Policy",
            "Units": 24.0,
            "SubPlanCode": "HLPL-SPEC",
            "SubplanType": "SPC",
            "Year": 2022,
            "Career": "Postgraduate"
        },
        {
            "Name": "Health and Medicine Honours Specialisation",
            "Units": 48.0,
            "SubPlanCode": "HLMD-HSPC",
            "SubplanType": "SPC",
            "Year": 2022,
            "Career": "Undergraduate"
        },
        {
            "Name": "History Honours",
            "Units": 48.0,
            "SubPlanCode": "HIST-HSPC",
            "SubplanType": "SPC",
            "Year": 2022,
            "Career": "Undergraduate"
        },
        {
            "Name": "Human Centre Design and  Software",
            "Units": 24.0,
            "SubPlanCode": "HCSD-SPEC",
            "SubplanType": "SPC",
            "Year": 2022,
            "Career": "Postgraduate"
        },
        {
            "Name": "Human Centred Design and Software Development",
            "Units": 24.0,
            "SubPlanCode": "HCSD-SPEC",
            "SubplanType": "SPC",
            "Year": 2022,
            "Career": "Postgraduate"
        },
        {
            "Name": "Human Evolution",
            "Units": 24.0,
            "SubPlanCode": "HUEV-SPEC",
            "SubplanType": "SPC",
            "Year": 2022,
            "Career": "Postgraduate"
        },
        {
            "Name": "Human Security Law",
            "Units": 24.0,
            "SubPlanCode": "HUST-SPEC",
            "SubplanType": "SPC",
            "Year": 2022,
            "Career": "Postgraduate"
        },
        {
            "Name": "Indigenous Policy and Development",
            "Units": 24.0,
            "SubPlanCode": "IPDV-SPEC",
            "SubplanType": "SPC",
            "Year": 2022,
            "Career": "Postgraduate"
        },
        {
            "Name": "Information and Human Centred Computing",
            "Units": 24.0,
            "SubPlanCode": "IHCC-SPEC",
            "SubplanType": "SPC",
            "Year": 2022,
            "Career": "Postgraduate"
        },
        {
            "Name": "Intangible Cultural Heritage",
            "Units": 24.0,
            "SubPlanCode": "INHC-SPEC",
            "SubplanType": "SPC",
            "Year": 2022,
            "Career": "Postgraduate"
        },
        {
            "Name": "Integrity and Anti-Corruption",
            "Units": 24.0,
            "SubPlanCode": "INAC-SPEC",
            "SubplanType": "SPC",
            "Year": 2022,
            "Career": "Postgraduate"
        },
        {
            "Name": "International Business",
            "Units": 24.0,
            "SubPlanCode": "BUSI-SPEC",
            "SubplanType": "SPC",
            "Year": 2022,
            "Career": "Postgraduate"
        },
        {
            "Name": "International Business Honours",
            "Units": 48.0,
            "SubPlanCode": "INBS-HSPC",
            "SubplanType": "SPC",
            "Year": 2022,
            "Career": "Undergraduate"
        },
        {
            "Name": "International Governance",
            "Units": 24.0,
            "SubPlanCode": "IRIG-SPEC",
            "SubplanType": "SPC",
            "Year": 2022,
            "Career": "Postgraduate"
        },
        {
            "Name": "International Law",
            "Units": 24.0,
            "SubPlanCode": "INTL-SPEC",
            "SubplanType": "SPC",
            "Year": 2022,
            "Career": "Postgraduate"
        },
        {
            "Name": "International Policy",
            "Units": 24.0,
            "SubPlanCode": "INPL-SPEC",
            "SubplanType": "SPC",
            "Year": 2022,
            "Career": "Postgraduate"
        },
        {
            "Name": "International Political Economy",
            "Units": 24.0,
            "SubPlanCode": "IRPE-SPEC",
            "SubplanType": "SPC",
            "Year": 2022,
            "Career": "Postgraduate"
        },
        {
            "Name": "International Relations",
            "Units": 48.0,
            "SubPlanCode": "IRH-HSPC",
            "SubplanType": "SPC",
            "Year": 2022,
            "Career": "Undergraduate"
        },
        {
            "Name": "International Relations Honours",
            "Units": 48.0,
            "SubPlanCode": "IRH-HSPC",
            "SubplanType": "SPC",
            "Year": 2022,
            "Career": "Undergraduate"
        },
        {
            "Name": "International Relations of the Asia-Pacific",
            "Units": 24.0,
            "SubPlanCode": "IRAP-SPEC",
            "SubplanType": "SPC",
            "Year": 2022,
            "Career": "Postgraduate"
        },
        {
            "Name": "International Security",
            "Units": 24.0,
            "SubPlanCode": "IRIS-SPEC",
            "SubplanType": "SPC",
            "Year": 2022,
            "Career": "Postgraduate"
        },
        {
            "Name": "International Trade and Finance",
            "Units": 24.0,
            "SubPlanCode": "ITFN-SPEC",
            "SubplanType": "SPC",
            "Year": 2022,
            "Career": "Postgraduate"
        },
        {
            "Name": "International and Comparative Law",
            "Units": 24.0,
            "SubPlanCode": "INTC-SPEC",
            "SubplanType": "SPC",
            "Year": 2022,
            "Career": "Undergraduate"
        },
        {
            "Name": "Italian Language and Culture",
            "Units": 24.0,
            "SubPlanCode": "ITAL-SPEC",
            "SubplanType": "SPC",
            "Year": 2022,
            "Career": ""
        },
        {
            "Name": "Language Studies Honours",
            "Units": 48.0,
            "SubPlanCode": "LANG-HSPC",
            "SubplanType": "SPC",
            "Year": 2022,
            "Career": "Undergraduate"
        },
        {
            "Name": "Law Reform, Environmental and Social Justice",
            "Units": 24.0,
            "SubPlanCode": "LRES-SPEC",
            "SubplanType": "SPC",
            "Year": 2022,
            "Career": "Undergraduate"
        },
        {
            "Name": "Leadership",
            "Units": 24.0,
            "SubPlanCode": "LEAD-SPEC",
            "SubplanType": "SPC",
            "Year": 2022,
            "Career": "Postgraduate"
        },
        {
            "Name": "Machine Learning",
            "Units": 24.0,
            "SubPlanCode": "MACL-SPEC",
            "SubplanType": "SPC",
            "Year": 2022,
            "Career": "Undergraduate"
        },
        {
            "Name": "Machine Learning",
            "Units": 24.0,
            "SubPlanCode": "MCHL-SPEC",
            "SubplanType": "SPC",
            "Year": 2022,
            "Career": "Postgraduate"
        },
        {
            "Name": "Macroeconomic Policy",
            "Units": 24.0,
            "SubPlanCode": "MAEC-SPEC",
            "SubplanType": "SPC",
            "Year": 2022,
            "Career": "Postgraduate"
        },
        {
            "Name": "Management Core",
            "Units": 24.0,
            "SubPlanCode": "MGMC-SPEC",
            "SubplanType": "SPC",
            "Year": 2022,
            "Career": "Postgraduate"
        },
        {
            "Name": "Management Essentials",
            "Units": 24.0,
            "SubPlanCode": "MGME-SPEC",
            "SubplanType": "SPC",
            "Year": 2022,
            "Career": "Postgraduate"
        },
        {
            "Name": "Management Honours",
            "Units": 48.0,
            "SubPlanCode": "MGMT-HSPC",
            "SubplanType": "SPC",
            "Year": 2022,
            "Career": "Undergraduate"
        },
        {
            "Name": "Marine Science Specialisation",
            "Units": 24.0,
            "SubPlanCode": "MARS-SPEC",
            "SubplanType": "SPC",
            "Year": 2022,
            "Career": "Undergraduate"
        },
        {
            "Name": "Marketing",
            "Units": 24.0,
            "SubPlanCode": "MKTG-SPEC",
            "SubplanType": "SPC",
            "Year": 2022,
            "Career": "Postgraduate"
        },
        {
            "Name": "Marketing Honours",
            "Units": 48.0,
            "SubPlanCode": "MKTG-HSPC",
            "SubplanType": "SPC",
            "Year": 2022,
            "Career": "Undergraduate"
        },
        {
            "Name": "Mathematical Physics",
            "Units": 24.0,
            "SubPlanCode": "MPHY-SPEC",
            "SubplanType": "SPC",
            "Year": 2022,
            "Career": "Undergraduate"
        },
        {
            "Name": "Mathematics Honours",
            "Units": 48.0,
            "SubPlanCode": "MATH-HSPC",
            "SubplanType": "SPC",
            "Year": 2022,
            "Career": "Undergraduate"
        },
        {
            "Name": "Medical Research Honours",
            "Units": 48.0,
            "SubPlanCode": "MEDR-HSPC",
            "SubplanType": "SPC",
            "Year": 2022,
            "Career": "Undergraduate"
        },
        {
            "Name": "Microbiology and Immunology",
            "Units": 24.0,
            "SubPlanCode": "MBIM-SPEC",
            "SubplanType": "SPC",
            "Year": 2022,
            "Career": "Undergraduate"
        },
        {
            "Name": "Microeconomic Policy",
            "Units": 24.0,
            "SubPlanCode": "MIEC-SPEC",
            "SubplanType": "SPC",
            "Year": 2022,
            "Career": "Postgraduate"
        },
        {
            "Name": "Middle Eastern and Central Asian Studies Honours",
            "Units": 48.0,
            "SubPlanCode": "MECA-HSPC",
            "SubplanType": "SPC",
            "Year": 2022,
            "Career": "Undergraduate"
        },
        {
            "Name": "Museum Education and Heritage Interpretation",
            "Units": 24.0,
            "SubPlanCode": "MEHI-SPEC",
            "SubplanType": "SPC",
            "Year": 2022,
            "Career": "Postgraduate"
        },
        {
            "Name": "Museums and Collections",
            "Units": 24.0,
            "SubPlanCode": "MUCO-SPEC",
            "SubplanType": "SPC",
            "Year": 2022,
            "Career": "Postgraduate"
        },
        {
            "Name": "Music Honours",
            "Units": 48.0,
            "SubPlanCode": "MUSI-HSPC",
            "SubplanType": "SPC",
            "Year": 2022,
            "Career": "Undergraduate"
        },
        {
            "Name": "Music Technology Honours",
            "Units": 48.0,
            "SubPlanCode": "MTEC-HSPC",
            "SubplanType": "SPC",
            "Year": 2022,
            "Career": "Undergraduate"
        },
        {
            "Name": "Musicology Honours",
            "Units": 48.0,
            "SubPlanCode": "MUSY-HSPC",
            "SubplanType": "SPC",
            "Year": 2022,
            "Career": "Undergraduate"
        },
        {
            "Name": "Neuroscience and Physiology",
            "Units": 24.0,
            "SubPlanCode": "NEUR-SPEC",
            "SubplanType": "SPC",
            "Year": 2022,
            "Career": "Undergraduate"
        },
        {
            "Name": "New Technologies Law",
            "Units": 24.0,
            "SubPlanCode": "TECH-SPEC",
            "SubplanType": "SPC",
            "Year": 2022,
            "Career": "Postgraduate"
        },
        {
            "Name": "Optics",
            "Units": 24.0,
            "SubPlanCode": "OPTC-SPEC",
            "SubplanType": "SPC",
            "Year": 2022,
            "Career": "Undergraduate"
        },
        {
            "Name": "Peace and Conflict Studies",
            "Units": 24.0,
            "SubPlanCode": "IRPC-SPEC",
            "SubplanType": "SPC",
            "Year": 2022,
            "Career": "Postgraduate"
        },
        {
            "Name": "Performance Honours",
            "Units": 48.0,
            "SubPlanCode": "PERF-HSPC",
            "SubplanType": "SPC",
            "Year": 2022,
            "Career": "Undergraduate"
        },
        {
            "Name": "Philosophy Honours",
            "Units": 48.0,
            "SubPlanCode": "PHIL-HSPC",
            "SubplanType": "SPC",
            "Year": 2022,
            "Career": "Undergraduate"
        },
        {
            "Name": "Physics Honours",
            "Units": 48.0,
            "SubPlanCode": "PHYS-HSPC",
            "SubplanType": "SPC",
            "Year": 2022,
            "Career": "Undergraduate"
        },
        {
            "Name": "Physics of the Earth Honours",
            "Units": 48.0,
            "SubPlanCode": "POTE-HSPC",
            "SubplanType": "SPC",
            "Year": 2022,
            "Career": "Undergraduate"
        },
        {
            "Name": "Plant Science",
            "Units": 24.0,
            "SubPlanCode": "PLNT-SPEC",
            "SubplanType": "SPC",
            "Year": 2022,
            "Career": "Undergraduate"
        },
        {
            "Name": "Policy Analysis",
            "Units": 24.0,
            "SubPlanCode": "POAN-SPEC",
            "SubplanType": "SPC",
            "Year": 2022,
            "Career": "Postgraduate"
        },
        {
            "Name": "Policy Communication",
            "Units": 24.0,
            "SubPlanCode": "POCM-SPEC",
            "SubplanType": "SPC",
            "Year": 2022,
            "Career": "Postgraduate"
        },
        {
            "Name": "Political Science Honours",
            "Units": 48.0,
            "SubPlanCode": "POLS-HSPC",
            "SubplanType": "SPC",
            "Year": 2022,
            "Career": "Undergraduate"
        },
        {
            "Name": "Politics and International Relations Honours",
            "Units": 48.0,
            "SubPlanCode": "PSIR-HSPC",
            "SubplanType": "SPC",
            "Year": 2022,
            "Career": "Undergraduate"
        },
        {
            "Name": "Population Change",
            "Units": 24.0,
            "SubPlanCode": "POPC-SPEC",
            "SubplanType": "SPC",
            "Year": 2022,
            "Career": "Postgraduate"
        },
        {
            "Name": "Population Health Honours",
            "Units": 48.0,
            "SubPlanCode": "POPH-HSPC",
            "SubplanType": "SPC",
            "Year": 2022,
            "Career": "Undergraduate"
        },
        {
            "Name": "Population Health Honours",
            "Units": 48.0,
            "SubPlanCode": "POPS-HSPC",
            "SubplanType": "SPC",
            "Year": 2022,
            "Career": ""
        },
        {
            "Name": "Primate and Human Behaviour",
            "Units": 24.0,
            "SubPlanCode": "PRHB-SPEC",
            "SubplanType": "SPC",
            "Year": 2022,
            "Career": "Postgraduate"
        },
        {
            "Name": "Private Commercial Law",
            "Units": 24.0,
            "SubPlanCode": "PRCO-SPEC",
            "SubplanType": "SPC",
            "Year": 2022,
            "Career": "Postgraduate"
        },
        {
            "Name": "Professional Computing",
            "Units": 24.0,
            "SubPlanCode": "PCOM-SPEC",
            "SubplanType": "SPC",
            "Year": 2022,
            "Career": "Postgraduate"
        },
        {
            "Name": "Professional Science Engagement",
            "Units": 24.0,
            "SubPlanCode": "PSCE-SPEC",
            "SubplanType": "SPC",
            "Year": 2022,
            "Career": "Undergraduate"
        },
        {
            "Name": "Project Management",
            "Units": 24.0,
            "SubPlanCode": "PROM-SPEC",
            "SubplanType": "SPC",
            "Year": 2022,
            "Career": "Postgraduate"
        },
        {
            "Name": "Project Management Essentials",
            "Units": 24.0,
            "SubPlanCode": "PMGE-SPEC",
            "SubplanType": "SPC",
            "Year": 2022,
            "Career": "Postgraduate"
        },
        {
            "Name": "Psychology",
            "Units": 24.0,
            "SubPlanCode": "PSYC-SPEC",
            "SubplanType": "SPC",
            "Year": 2022,
            "Career": "Undergraduate"
        },
        {
            "Name": "Psychology Honours",
            "Units": 48.0,
            "SubPlanCode": "PSYC-HSPC",
            "SubplanType": "SPC",
            "Year": 2022,
            "Career": "Undergraduate"
        },
        {
            "Name": "Public Finance",
            "Units": 24.0,
            "SubPlanCode": "PUFN-SPEC",
            "SubplanType": "SPC",
            "Year": 2022,
            "Career": "Postgraduate"
        },
        {
            "Name": "Public Law",
            "Units": 24.0,
            "SubPlanCode": "PULA-SPEC",
            "SubplanType": "SPC",
            "Year": 2022,
            "Career": "Undergraduate"
        },
        {
            "Name": "Public Law",
            "Units": 24.0,
            "SubPlanCode": "PUBL-SPEC",
            "SubplanType": "SPC",
            "Year": 2022,
            "Career": "Postgraduate"
        },
        {
            "Name": "Science Communication Honours",
            "Units": 48.0,
            "SubPlanCode": "SCOM-HSPC",
            "SubplanType": "SPC",
            "Year": 2022,
            "Career": "Undergraduate"
        },
        {
            "Name": "Science Communication Honours",
            "Units": 48.0,
            "SubPlanCode": "SCIM-HSPC",
            "SubplanType": "SPC",
            "Year": 2022,
            "Career": ""
        },
        {
            "Name": "Science Honours",
            "Units": 48.0,
            "SubPlanCode": "SCNC-HSPC",
            "SubplanType": "SPC",
            "Year": 2022,
            "Career": "Undergraduate"
        },
        {
            "Name": "Security Studies Honours",
            "Units": 48.0,
            "SubPlanCode": "SEST-HSPC",
            "SubplanType": "SPC",
            "Year": 2022,
            "Career": "Undergraduate"
        },
        {
            "Name": "Social Policy",
            "Units": 24.0,
            "SubPlanCode": "SOPL-SPEC",
            "SubplanType": "SPC",
            "Year": 2022,
            "Career": "Postgraduate"
        },
        {
            "Name": "Social Research Methods",
            "Units": 24.0,
            "SubPlanCode": "SORM-SPEC",
            "SubplanType": "SPC",
            "Year": 2022,
            "Career": "Postgraduate"
        },
        {
            "Name": "Society and Environment",
            "Units": 24.0,
            "SubPlanCode": "SOEN-SPEC",
            "SubplanType": "SPC",
            "Year": 2022,
            "Career": "Postgraduate"
        },
        {
            "Name": "Sociology Honours",
            "Units": 48.0,
            "SubPlanCode": "SOCY-HSPC",
            "SubplanType": "SPC",
            "Year": 2022,
            "Career": "Undergraduate"
        },
        {
            "Name": "Software Engineering",
            "Units": 24.0,
            "SubPlanCode": "SENG-SPEC",
            "SubplanType": "SPC",
            "Year": 2022,
            "Career": "Postgraduate"
        },
        {
            "Name": "Statistics",
            "Units": 24.0,
            "SubPlanCode": "STAT-SPEC",
            "SubplanType": "SPC",
            "Year": 2022,
            "Career": "Postgraduate"
        },
        {
            "Name": "Statistics Honours",
            "Units": 48.0,
            "SubPlanCode": "STAT-HSPC",
            "SubplanType": "SPC",
            "Year": 2022,
            "Career": "Undergraduate"
        },
        {
            "Name": "Systems and Architecture",
            "Units": 24.0,
            "SubPlanCode": "SYAR-SPEC",
            "SubplanType": "SPC",
            "Year": 2022,
            "Career": "Undergraduate"
        },
        {
            "Name": "Theoretical Computer Science",
            "Units": 24.0,
            "SubPlanCode": "THCS-SPEC",
            "SubplanType": "SPC",
            "Year": 2022,
            "Career": "Undergraduate"
        },
        {
            "Name": "World Affairs",
            "Units": 24.0,
            "SubPlanCode": "IRWA-SPEC",
            "SubplanType": "SPC",
            "Year": 2022,
            "Career": "Postgraduate"
        }
    ],
    "Suggestion": null
}
